pynssp/__init__.py
pynssp/data.py
pynssp/utils.py
pynssp/core/__init__.py
pynssp/core/constants.py
pynssp/core/container.py
pynssp/core/credentials.py
pynssp/core/token.py
pynssp/data/nssp_stopwords.csv
pynssp/data/simulated_ts.csv
pynssp/detectors/__init__.py
pynssp/detectors/ewma.py
pynssp/detectors/nbinom.py
pynssp/detectors/regression.py
pynssp/detectors/serfling.py
pynssp/detectors/switch.py
pynssp/detectors/trend.py
pynssp-0.1.0.dist-info/AUTHORS.md
pynssp-0.1.0.dist-info/LICENSE
pynssp-0.1.0.dist-info/METADATA
pynssp-0.1.0.dist-info/WHEEL
pynssp-0.1.0.dist-info/top_level.txt
pynssp-0.1.0.dist-info/RECORD
