Metadata-Version: 2.1
Name: pynssp
Version: 0.1.0
Summary: A Python package for the National Syndromic Surveillance Program (NSSP) and its Community of Practice. A collection of classes and methods to advance the practice of Syndromic Surveillance.
Home-page: https://github.com/cdcgov/pynssp
Author: Gbedegnon Roseric Azondekon
Author-email: gazondekon@cdc.gov, roseric_2000@yahoo.fr
License: Apache Software License 2.0
Keywords: pynssp
Classifier: Development Status :: 2 - Pre-Alpha
Classifier: Intended Audience :: Developers
Classifier: License :: OSI Approved :: Apache Software License
Classifier: Natural Language :: English
Classifier: Programming Language :: Python :: 3
Classifier: Programming Language :: Python :: 3.7
Classifier: Programming Language :: Python :: 3.8
Classifier: Programming Language :: Python :: 3.9
Classifier: Programming Language :: Python :: 3.10
Classifier: Programming Language :: Python :: 3.11
Requires-Python: >=3.7
License-File: LICENSE
License-File: AUTHORS.md
Requires-Dist: pandas
Requires-Dist: cryptography
Requires-Dist: pillow
Requires-Dist: scikit-image
Requires-Dist: matplotlib
Requires-Dist: statsmodels
Requires-Dist: scipy
Requires-Dist: datetime
